{
    "key": "group_60a7db56819a0",
    "title": "Page Options",
    "fields": [
        {
            "key": "field_60a7db7de872c",
            "label": "Header CTA Text",
            "name": "header_cta_text",
            "type": "text",
            "instructions": "This will override the text in the header call to action button",
            "required": 0,
            "conditional_logic": 0,
            "wrapper": {
                "width": "",
                "class": "",
                "id": ""
            },
            "default_value": "",
            "placeholder": "",
            "prepend": "",
            "append": "",
            "maxlength": ""
        }
    ],
    "location": [
        [
            {
                "param": "post_type",
                "operator": "==",
                "value": "page"
            }
        ],
        [
            {
                "param": "post_type",
                "operator": "==",
                "value": "service-areas"
            }
        ],
        [
            {
                "param": "post_type",
                "operator": "==",
                "value": "services"
            }
        ],
        [
            {
                "param": "post_type",
                "operator": "==",
                "value": "pests"
            }
        ]
    ],
    "menu_order": 0,
    "position": "side",
    "style": "default",
    "label_placement": "top",
    "instruction_placement": "label",
    "hide_on_screen": "",
    "active": true,
    "description": "",
    "modified": 1621613590
}